drb/drivers/yaml/__init__.py
drb/drivers/yaml/_version.py
drb/drivers/yaml/yaml.py
drb/topics/yaml/__init__.py
drb_driver_yaml-1.3.0.dist-info/LICENCE.txt
drb_driver_yaml-1.3.0.dist-info/METADATA
drb_driver_yaml-1.3.0.dist-info/WHEEL
drb_driver_yaml-1.3.0.dist-info/entry_points.txt
drb_driver_yaml-1.3.0.dist-info/top_level.txt
drb_driver_yaml-1.3.0.dist-info/RECORD
